reverse_communication_iterative_solver/__init__.py
reverse_communication_iterative_solver/__main__.py
reverse_communication_iterative_solver/cli.py
reverse_communication_iterative_solver-0.0.1.dist-info/AUTHORS.rst
reverse_communication_iterative_solver-0.0.1.dist-info/LICENSE
reverse_communication_iterative_solver-0.0.1.dist-info/METADATA
reverse_communication_iterative_solver-0.0.1.dist-info/WHEEL
reverse_communication_iterative_solver-0.0.1.dist-info/entry_points.txt
reverse_communication_iterative_solver-0.0.1.dist-info/top_level.txt
reverse_communication_iterative_solver-0.0.1.dist-info/RECORD
