Metadata-Version: 2.1
Name: reverse-communication-iterative-solver
Version: 0.0.1
Summary: Python package/template to build iterative solver via reverse communication and classes
Home-page: https://github.com/enricofacca/python-reverse_communication_iterative_solver
Author: Enrico Facca
Author-email: enrico.facca@gmail.com
License: LGPL-3.0-or-later
Project-URL: Documentation, https://python-reverse_communication_iterative_solver.readthedocs.io/
Project-URL: Changelog, https://python-reverse_communication_iterative_solver.readthedocs.io/en/latest/changelog.html
Project-URL: Issue Tracker, https://github.com/enricofacca/python-reverse_communication_iterative_solver/issues
Platform: UNKNOWN
Classifier: Development Status :: 5 - Production/Stable
Classifier: Intended Audience :: Developers
Classifier: License :: OSI Approved :: GNU Lesser General Public License v3 or later (LGPLv3+)
Classifier: Operating System :: Unix
Classifier: Operating System :: POSIX
Classifier: Operating System :: Microsoft :: Windows
Classifier: Programming Language :: Python
Classifier: Programming Language :: Python :: 3
Classifier: Programming Language :: Python :: 3 :: Only
Classifier: Programming Language :: Python :: 3.6
Classifier: Programming Language :: Python :: 3.7
Classifier: Programming Language :: Python :: 3.8
Classifier: Programming Language :: Python :: 3.9
Classifier: Programming Language :: Python :: 3.10
Classifier: Programming Language :: Python :: Implementation :: CPython
Classifier: Programming Language :: Python :: Implementation :: PyPy
Classifier: Topic :: Utilities
Requires-Python: >=3.6
